calimero/__init__.py
calimero/client.py
calimero/types.py
calimero/ws_subscriptions_client.py
tests/conftest.py
tests/test_application_workflows.py
tests/test_basic_functionality.py
tests/test_basic_imports.py
tests/test_context_workflows.py
tests/test_execute_workflows.py
tests/test_identity_workflows.py
calimero_client_py-0.2.2.dist-info/METADATA
calimero_client_py-0.2.2.dist-info/WHEEL
calimero_client_py-0.2.2.dist-info/top_level.txt
calimero_client_py-0.2.2.dist-info/RECORD
