Metadata-Version: 2.4
Name: calimero-client-py
Version: 0.2.2
Summary: Python client SDK for Calimero Network
Home-page: https://github.com/calimero-network/calimero-client-py
Author: Calimero Network
Author-email: Calimero Network <support@calimero.network>
Classifier: Development Status :: 3 - Alpha
Classifier: Intended Audience :: Developers
Classifier: License :: OSI Approved :: MIT License
Classifier: Programming Language :: Python :: 3
Classifier: Programming Language :: Python :: 3.9
Classifier: Programming Language :: Python :: 3.10
Classifier: Programming Language :: Python :: 3.11
Classifier: Programming Language :: Python :: 3.12
Classifier: Programming Language :: Python :: 3.13
Requires-Python: >=3.9
Requires-Dist: requests>=2.31.0
Requires-Dist: websockets>=12.0
Requires-Dist: base58>=2.1.1
Requires-Dist: pydantic>=2.5.0
Requires-Dist: aiohttp>=3.9.0
Requires-Dist: toml>=0.10.2
Requires-Dist: pynacl>=1.5.0
Requires-Dist: calimero-client-py-bindings>=0.2.2
Provides-Extra: dev
Requires-Dist: pytest; extra == "dev"
Requires-Dist: pytest-asyncio>=0.26.0; extra == "dev"
Requires-Dist: merobox>=0.1.0; extra == "dev"
Requires-Dist: black; extra == "dev"
Requires-Dist: pre-commit; extra == "dev"
Dynamic: author
Dynamic: home-page
Dynamic: requires-python
